evesso/__init__.py
evesso/authorize.py
evesso/cache.py
evesso/const.py
evesso/refresh.py
evesso/sso.py
evesso/callback/__init__.py
evesso/callback/index.html
evesso/callback/server.py
evesso-0.1.3.dist-info/LICENSE
evesso-0.1.3.dist-info/METADATA
evesso-0.1.3.dist-info/WHEEL
evesso-0.1.3.dist-info/top_level.txt
evesso-0.1.3.dist-info/RECORD
