Metadata-Version: 2.1
Name: evesso
Version: 0.1.3
Summary: Python SSO Authorization for Eve Online API applications
Home-page: https://github.com/harrelchris/evesso
Author: harrelchris
Classifier: Programming Language :: Python :: 3
Classifier: License :: OSI Approved :: MIT License
Classifier: Operating System :: OS Independent
Requires-Python: >=3.6
License-File: LICENSE
Requires-Dist: requests
